rrule_humanize/__init__.py
rrule_humanize/humanize.py
rrule_humanize-0.1.0.dist-info/licenses/LICENSE
rrule_humanize-0.1.0.dist-info/METADATA
rrule_humanize-0.1.0.dist-info/WHEEL
rrule_humanize-0.1.0.dist-info/top_level.txt
rrule_humanize-0.1.0.dist-info/RECORD
