Metadata-Version: 2.4
Name: rrule-humanize
Version: 0.1.0
Summary: A Python library to convert RRULE strings to human-readable text
Home-page: https://github.com/progpeter/rrule-humanize
Author: PeterS
Author-email: PeterS <eng.peter.habib@gmail.com>
License-Expression: MIT
Project-URL: Homepage, https://github.com/progpeter/rrule-humanize
Project-URL: Repository, https://github.com/progpeter/rrule-humanize
Classifier: Development Status :: 3 - Alpha
Classifier: Intended Audience :: Developers
Classifier: Operating System :: OS Independent
Classifier: Programming Language :: Python :: 3
Classifier: Programming Language :: Python :: 3.7
Classifier: Programming Language :: Python :: 3.8
Classifier: Programming Language :: Python :: 3.9
Classifier: Programming Language :: Python :: 3.10
Classifier: Programming Language :: Python :: 3.11
Requires-Python: >=3.7
License-File: LICENSE
Requires-Dist: python-dateutil>=2.8.0
Dynamic: author
Dynamic: home-page
Dynamic: license-file
Dynamic: requires-python
